coordinatus/__init__.py
coordinatus/coordinate.py
coordinatus/frame.py
coordinatus/transforms.py
coordinatus/types.py
coordinatus/visualization.py
coordinatus-0.2.0.dist-info/WHEEL
coordinatus-0.2.0.dist-info/METADATA
coordinatus-0.2.0.dist-info/RECORD
