Metadata-Version: 2.3
Name: coordinatus
Version: 0.2.0
Summary: A library for working with hierarchical coordinate systems and transformations
Author: Manu Gira
Author-email: Manu Gira <manu.gira@outlook.com>
Requires-Dist: numpy>=2.4.0
Requires-Dist: matplotlib>=3.10.8 ; extra == 'plotting'
Requires-Python: >=3.12
Project-URL: Homepage, https://github.com/ManuGira/Coordinatus
Project-URL: Repository, https://github.com/ManuGira/Coordinatus
Provides-Extra: plotting
